{
 "actions": [],
 "allow_rename": 1,
 "creation": "2023-07-31 10:13:10.960678",
 "doctype": "DocType",
 "editable_grid": 1,
 "engine": "InnoDB",
 "field_order": [
  "job_order",
  "item",
  "machine",
  "operation",
  "operation_name",
  "cycle_time"
 ],
 "fields": [
  {
   "fieldname": "item",
   "fieldtype": "Link",
   "in_list_view": 1,
   "label": "Finished Item",
   "options": "Item",
   "reqd": 1
  },
  {
   "fieldname": "machine",
   "fieldtype": "Link",
   "in_list_view": 1,
   "label": "Machine Name",
   "options": "Machine",
   "reqd": 1
  },
  {
   "fieldname": "operation",
   "fieldtype": "Link",
   "in_list_view": 1,
   "label": "Operation",
   "options": "Operation Master",
   "reqd": 1
  },
  {
   "fieldname": "cycle_time",
   "fieldtype": "Float",
   "in_list_view": 1,
   "label": "Cycle Time",
   "precision": "2",
   "reqd": 1
  },
  {
   "fieldname": "job_order",
   "fieldtype": "Link",
   "label": "Job Order",
   "options": "Job Order"
  },
  {
   "fetch_from": "operation.operation",
   "fieldname": "operation_name",
   "fieldtype": "Data",
   "label": "Operation Name",
   "read_only": 1
  }
 ],
 "index_web_pages_for_search": 1,
 "istable": 1,
 "links": [],
 "modified": "2023-11-29 11:42:41.736433",
 "modified_by": "Administrator",
 "module": "Ms Production",
 "name": "Item operations",
 "owner": "Administrator",
 "permissions": [],
 "sort_field": "modified",
 "sort_order": "DESC",
 "states": []
}